odds_api/__init__.py
odds_api/async_client.py
odds_api/client.py
odds_api/constants.py
odds_api/exceptions.py
odds_api/py.typed
odds_api_io-1.0.0.dist-info/licenses/LICENSE
odds_api_io-1.0.0.dist-info/METADATA
odds_api_io-1.0.0.dist-info/WHEEL
odds_api_io-1.0.0.dist-info/top_level.txt
odds_api_io-1.0.0.dist-info/RECORD
