Metadata-Version: 2.4
Name: odds-api-io
Version: 1.0.0
Summary: Official Python SDK for Odds-API.io - Real-time sports betting odds from 250+ bookmakers
Author-email: "Odds-API.io" <hello@odds-api.io>
License: MIT
Project-URL: Homepage, https://odds-api.io
Project-URL: Documentation, https://docs.odds-api.io
Project-URL: Repository, https://github.com/odds-api-io/odds-api-python
Project-URL: Issues, https://github.com/odds-api-io/odds-api-python/issues
Keywords: odds,sports,betting,api,odds-api,arbitrage,value-bets,bookmakers,sportsbook
Classifier: Development Status :: 5 - Production/Stable
Classifier: Intended Audience :: Developers
Classifier: License :: OSI Approved :: MIT License
Classifier: Operating System :: OS Independent
Classifier: Programming Language :: Python :: 3
Classifier: Programming Language :: Python :: 3.8
Classifier: Programming Language :: Python :: 3.9
Classifier: Programming Language :: Python :: 3.10
Classifier: Programming Language :: Python :: 3.11
Classifier: Programming Language :: Python :: 3.12
Classifier: Topic :: Software Development :: Libraries :: Python Modules
Classifier: Topic :: Internet :: WWW/HTTP
Requires-Python: >=3.8
License-File: LICENSE
Requires-Dist: requests>=2.25.0
Requires-Dist: aiohttp>=3.8.0
Provides-Extra: dev
Requires-Dist: pytest>=7.0.0; extra == "dev"
Requires-Dist: pytest-asyncio>=0.21.0; extra == "dev"
Requires-Dist: black>=23.0.0; extra == "dev"
Requires-Dist: mypy>=1.0.0; extra == "dev"
Requires-Dist: ruff>=0.1.0; extra == "dev"
Dynamic: license-file
